{
  "gitSyncId": "661eca10b7e3352fe43e8a8c_661eca11b7e3352fe43e8a9a",
  "id": "Домой_last_data_update",
  "pluginId": "mysql-plugin",
  "pluginType": "DB",
  "unpublishedAction": {
    "actionConfiguration": {
      "body": "SELECT * FROM appsmith_last_data_update;",
      "encodeParamsToggle": true,
      "paginationType": "NONE",
      "pluginSpecifiedTemplates": [
        {
          "value": true
        }
      ],
      "timeoutInMillisecond": 10000
    },
    "confirmBeforeExecute": false,
    "datasource": {
      "id": "contest",
      "isAutoGenerated": false,
      "name": "contest",
      "pluginId": "mysql-plugin"
    },
    "dynamicBindingPathList": [],
    "executeOnLoad": true,
    "name": "last_data_update",
    "pageId": "Домой",
    "userSetOnLoad": false
  }
}