{
  "gitSyncId": "661eca10b7e3352fe43e8a8c_c8f5c12a-3bff-4223-ac6a-f40adbe8c1d2",
  "id": "Аналитика_participants",
  "pluginId": "mysql-plugin",
  "pluginType": "DB",
  "unpublishedAction": {
    "actionConfiguration": {
      "body": "SELECT \n\tun.user_id\n\t, un.nickname\nFROM user_nickname un\nwhere un.is_active = 1\norder by un.nickname asc\n;",
      "encodeParamsToggle": true,
      "paginationType": "NONE",
      "pluginSpecifiedTemplates": [
        {
          "value": true
        }
      ],
      "timeoutInMillisecond": 10000
    },
    "confirmBeforeExecute": false,
    "datasource": {
      "id": "contest",
      "isAutoGenerated": false,
      "name": "contest",
      "pluginId": "mysql-plugin"
    },
    "dynamicBindingPathList": [],
    "name": "participants",
    "pageId": "Аналитика",
    "runBehaviour": "ON_PAGE_LOAD",
    "userSetOnLoad": false
  }
}